iktomi/__init__.py
iktomi/cms/__init__.py
iktomi/cms/ajax_file_upload.py
iktomi/cms/app.py
iktomi/cms/flashmessages.py
iktomi/cms/helploader.py
iktomi/cms/i18n_stream.py
iktomi/cms/list_edit.py
iktomi/cms/loner.py
iktomi/cms/menu.py
iktomi/cms/packer.py
iktomi/cms/preview.py
iktomi/cms/stream.py
iktomi/cms/stream_actions.py
iktomi/cms/stream_app.py
iktomi/cms/stream_handlers.py
iktomi/cms/stream_sortables.py
iktomi/cms/auth/__init__.py
iktomi/cms/auth/models.py
iktomi/cms/auth/stream.py
iktomi/cms/auth/views.py
iktomi/cms/edit_log/__init__.py
iktomi/cms/edit_log/forms.py
iktomi/cms/edit_log/models.py
iktomi/cms/edit_log/views.py
iktomi/cms/editor_notes/__init__.py
iktomi/cms/editor_notes/fields.py
iktomi/cms/editor_notes/models.py
iktomi/cms/editor_notes/views.py
iktomi/cms/forms/__init__.py
iktomi/cms/forms/convs.py
iktomi/cms/forms/fields.py
iktomi/cms/forms/files.py
iktomi/cms/forms/widgets.py
iktomi/cms/item_lock/__init__.py
iktomi/cms/item_lock/base.py
iktomi/cms/item_lock/memcached.py
iktomi/cms/item_lock/redis.py
iktomi/cms/item_lock/views.py
iktomi/cms/models/__init__.py
iktomi/cms/models/autosave.py
iktomi/cms/models/base.py
iktomi/cms/publishing/__init__.py
iktomi/cms/publishing/files.py
iktomi/cms/publishing/i18n_loner.py
iktomi/cms/publishing/i18n_stream.py
iktomi/cms/publishing/loner.py
iktomi/cms/publishing/model.py
iktomi/cms/publishing/stream.py
iktomi/cms/publishing/stream_sortables.py
iktomi/cms/publishing/views.py
iktomi/cms/static/css/Manifest
iktomi/cms/static/css/ajax_fileinput.css
iktomi/cms/static/css/aqua.css
iktomi/cms/static/css/button_select.css
iktomi/cms/static/css/buttons-flat.css
iktomi/cms/static/css/calendar.css
iktomi/cms/static/css/collapsable_block.css
iktomi/cms/static/css/crop.css
iktomi/cms/static/css/dashboard.css
iktomi/cms/static/css/edit_log.css
iktomi/cms/static/css/editor_notes.css
iktomi/cms/static/css/fieldlist.css
iktomi/cms/static/css/fieldset-line.css
iktomi/cms/static/css/flash.css
iktomi/cms/static/css/help.css
iktomi.cms-0.2.12.dist-info/METADATA
iktomi.cms-0.2.12.dist-info/WHEEL
iktomi.cms-0.2.12.dist-info/top_level.txt
iktomi.cms-0.2.12.dist-info/RECORD
